alfinx_autho/__init__.py
alfinx_autho/main.py
alfinx_autho-0.1.5.dist-info/licenses/LICENSE
alfinx_autho-0.1.5.dist-info/METADATA
alfinx_autho-0.1.5.dist-info/WHEEL
alfinx_autho-0.1.5.dist-info/top_level.txt
alfinx_autho-0.1.5.dist-info/RECORD
