Metadata-Version: 2.4
Name: alfinx_autho
Version: 0.1.5
Summary: HTTP headers auto detection tool.
Author: Maharram Mansimov
Author-email: maharram@example.com
Requires-Python: >=3.8
License-File: LICENSE
Requires-Dist: fastapi
Requires-Dist: httpx
Dynamic: author
Dynamic: author-email
Dynamic: description
Dynamic: description-content-type
Dynamic: license-file
Dynamic: requires-dist
Dynamic: requires-python
Dynamic: summary
